CHANGES.txt
LICENSE.txt
README.txt
bootstrap.py
buildout.cfg
setup.py
src/megrok/__init__.py
src/megrok.rendersource.egg-info/PKG-INFO
src/megrok.rendersource.egg-info/SOURCES.txt
src/megrok.rendersource.egg-info/dependency_links.txt
src/megrok.rendersource.egg-info/entry_points.txt
src/megrok.rendersource.egg-info/namespace_packages.txt
src/megrok.rendersource.egg-info/not-zip-safe
src/megrok.rendersource.egg-info/requires.txt
src/megrok.rendersource.egg-info/top_level.txt
src/megrok/rendersource/__init__.py
src/megrok/rendersource/configure.zcml
src/megrok/rendersource/ftesting.zcml
src/megrok/rendersource/rest.py
src/megrok/rendersource/ftests/__init__.py
src/megrok/rendersource/ftests/tests_functional.py
src/megrok/rendersource/ftests/directives/__init__.py
src/megrok/rendersource/ftests/directives/app.py
src/megrok/rendersource/ftests/directives/app_templates/base.rst
src/megrok/rendersource/ftests/directives/app_templates/include.txt
src/megrok/rendersource/ftests/directives/app_templates/index.pt
src/megrok/rendersource/ftests/directives/static/README.txt
src/megrok/rendersource/ftests/directives/static/grok.css