Metadata-Version: 1.0
Name: megrok.rendersource
Version: 0.5.1
Summary: Grok source renderers
Home-page: UNKNOWN
Author: d2m
Author-email: michael@d2m.at
License: ZPL
Platform: UNKNOWN
